handybelt/__init__.py
handybelt-0.0.1.dist-info/METADATA
handybelt-0.0.1.dist-info/RECORD
handybelt-0.0.1.dist-info/WHEEL
handybelt-0.0.1.dist-info/top_level.txt
